{
  "setting": {},
  "condition": {
    "miniprogram": {
      "list": [
        {
          "name": "",
          "pathName": "pages/device/index",
          "query": "",
          "launchMode": "default",
          "scene": null
        },
        {
          "name": "",
          "pathName": "pages/pilot/index",
          "query": "",
          "launchMode": "default",
          "scene": null
        },
        {
          "name": "",
          "pathName": "pages/current/index",
          "query": "",
          "launchMode": "default",
          "scene": null
        },
        {
          "name": "",
          "pathName": "subpackageA/pages/reported/index",
          "query": "",
          "launchMode": "default",
          "scene": null
        },
        {
          "name": "",
          "pathName": "subpackageA/pages/donePromote/index",
          "query": "",
          "launchMode": "default",
          "scene": null
        },
        {
          "name": "",
          "pathName": "subpackageA/pages/process/index",
          "query": "",
          "launchMode": "default",
          "scene": null
        },
        {
          "name": "",
          "pathName": "pages/proList/index",
          "query": "",
          "launchMode": "default",
          "scene": null
        },
        {
          "name": "",
          "pathName": "subpackageA/pages/orderDetails/index",
          "query": "",
          "launchMode": "default",
          "scene": null
        },
        {
          "name": "",
          "pathName": "pages/my/index",
          "query": "",
          "launchMode": "default",
          "scene": null
        },
        {
          "name": "",
          "pathName": "pages/login/index",
          "query": "",
          "launchMode": "default",
          "scene": null
        },
        {
          "name": "",
          "pathName": "pages/test/index",
          "query": "",
          "launchMode": "default",
          "scene": null
        },
        {
          "name": "",
          "pathName": "subpackageA/pages/reported/index",
          "query": "",
          "launchMode": "default",
          "scene": null
        },
        {
          "name": "",
          "pathName": "pages/proList/index",
          "query": "",
          "launchMode": "default",
          "scene": null
        },
        {
          "name": "",
          "pathName": "subpackageA/pages/process/index",
          "query": "",
          "launchMode": "default",
          "scene": null
        }
      ]
    }
  },
  "description": "项目私有配置文件。此文件中的内容将覆盖 project.config.json 中的相同字段。项目的改动优先同步到此文件中。详见文档：https://developers.weixin.qq.com/miniprogram/dev/devtools/projectconfig.html"
}